COPYING
MANIFEST.in
README.ipynb
README.md
ToolsLibrary.py
VERSION
requirements.remote.txt
requirements.robotshell.txt
requirements.txt
setup.cfg
setup.py
tox.ini
zetup.cfg
robotframework_tools.egg-info/PKG-INFO
robotframework_tools.egg-info/SOURCES.txt
robotframework_tools.egg-info/dependency_links.txt
robotframework_tools.egg-info/requires.txt
robotframework_tools.egg-info/top_level.txt
robotshell/__init__.py
robotshell/base.py
robotshell/extension.py
robotshell/library.py
robotshell/result.py
robotshell/shell.py
robotshell/magic/__init__.py
robotshell/magic/base.py
robotshell/magic/keyword.py
robotshell/magic/robot.py
robotshell/magic/variable.py
robottools/__init__.py
robottools/zetup_config.py
robottools/libdoc/__init__.py
robottools/libdoc/html.py
robottools/library/__init__.py
robottools/library/base.py
robottools/library/context/__init__.py
robottools/library/context/method.py
robottools/library/inspector/__init__.py
robottools/library/inspector/arguments.py
robottools/library/inspector/keyword.py
robottools/library/inspector/multi.py
robottools/library/keywords/__init__.py
robottools/library/keywords/deco.py
robottools/library/keywords/errors.py
robottools/library/keywords/utils.py
robottools/library/session/__init__.py
robottools/library/session/meta.py
robottools/library/session/metaoptions.py
robottools/remote/__init__.py
robottools/remote/keywords.py
robottools/remote/library.py
robottools/testrobot/__init__.py
robottools/testrobot/context.py
robottools/testrobot/highlighting.py
robottools/testrobot/keyword.py
robottools/testrobot/library.py
robottools/testrobot/output.py
robottools/testrobot/result.py
robottools/testrobot/variables.py
robottools/utils/__init__.py
robottools/utils/normbool.py
robottools/utils/normdict.py
robottools/utils/normstr.py
test/test_library.py
test/test_robottools.py