Metadata-Version: 1.1
Name: robotframework-tools
Version: 0.1a138
Summary: Python Tools for Robot Framework and Test Libraries.
Home-page: http://bitbucket.org/userzimmermann/robotframework-tools
Author: Stefan Zimmermann
Author-email: zimmermann.code@gmail.com
License: GPLv3
Keywords: robottools,robot,framework,robotframework,tools,test,automation,testautomation,testlibrary,testcase,keyword,pybot,robotshell,ipython,python3
Platform: UNKNOWN
Classifier: Development Status :: 3 - Alpha
Classifier: Intended Audience :: Developers
Classifier: License :: OSI Approved :: GNU General Public License (GPL)
Classifier: Operating System :: OS Independent
Classifier: Topic :: Software Development
Classifier: Topic :: Utilities
Classifier: Programming Language :: Python
Classifier: Programming Language :: Python :: 2.7
Classifier: Programming Language :: Python :: 3.3
Classifier: Programming Language :: Python :: 3.4
